odoo/addons/web_domain_field_example/README.rst
odoo/addons/web_domain_field_example/__init__.py
odoo/addons/web_domain_field_example/__manifest__.py
odoo/addons/web_domain_field_example/demo/product_demonstration.xml
odoo/addons/web_domain_field_example/i18n/de.po
odoo/addons/web_domain_field_example/i18n/fr.po
odoo/addons/web_domain_field_example/i18n/pt_BR.po
odoo/addons/web_domain_field_example/i18n/web_domain_field_example.pot
odoo/addons/web_domain_field_example/models/__init__.py
odoo/addons/web_domain_field_example/models/product_demonstration.py
odoo/addons/web_domain_field_example/models/product_selection_example.py
odoo/addons/web_domain_field_example/readme/CONTRIBUTORS.rst
odoo/addons/web_domain_field_example/readme/DESCRIPTION.rst
odoo/addons/web_domain_field_example/readme/USAGE.rst
odoo/addons/web_domain_field_example/security/ir.model.access.csv
odoo/addons/web_domain_field_example/static/description/icon.png
odoo/addons/web_domain_field_example/static/description/index.html
odoo/addons/web_domain_field_example/views/menu.xml
odoo/addons/web_domain_field_example/views/product_selection_example.xml
odoo12_addon_web_domain_field_example-12.0.1.0.0.99.dev10.dist-info/METADATA
odoo12_addon_web_domain_field_example-12.0.1.0.0.99.dev10.dist-info/WHEEL
odoo12_addon_web_domain_field_example-12.0.1.0.0.99.dev10.dist-info/top_level.txt
odoo12_addon_web_domain_field_example-12.0.1.0.0.99.dev10.dist-info/RECORD
